f_bomb/__init__.py
f_bomb/f_bomb.py
f_bomb-0.0.1.dist-info/licenses/LICENSE
f_bomb-0.0.1.dist-info/METADATA
f_bomb-0.0.1.dist-info/WHEEL
f_bomb-0.0.1.dist-info/top_level.txt
f_bomb-0.0.1.dist-info/RECORD
