Metadata-Version: 2.4
Name: f_bomb
Version: 0.0.1
Summary: When you need an f-bomb in your code, look no further.
Author-email: Charles Givre <charles.givre@gtkcyber.com>
License-Expression: MIT
Project-URL: Homepage, https://github.com/seatgeek/thefuzz
Classifier: Intended Audience :: Developers
Classifier: Programming Language :: Python
Classifier: Programming Language :: Python :: 3
Classifier: Programming Language :: Python :: 3.8
Classifier: Programming Language :: Python :: 3.9
Classifier: Programming Language :: Python :: 3.10
Classifier: Programming Language :: Python :: 3.11
Classifier: Programming Language :: Python :: 3.12
Classifier: Programming Language :: Python :: 3.13
Classifier: Programming Language :: Python :: 3 :: Only
Requires-Python: >=3.8
License-File: LICENSE
Requires-Dist: rapidfuzz<4.0.0,>=3.0.0
Dynamic: license-file
